{
  "company_id": "writer",
  "company_name": "Writer",
  "source_homepage": "https://writer.com",
  "crawled_at": "2025-11-20T03:42:15+00:00Z",
  "run_type": "full-load",
  "output_dir": "/opt/airflow/data/raw/writer/2025-11-20",
  "content_sha256": "bad60d73c2af7c4e784254377eb6066bef4bc3b2035748275882572bab76cc37",
  "content_length": 2584692,
  "parser": "lab1_scraper",
  "version": 1,
  "scraper_result": {
    "company_id": "writer",
    "company_name": "Writer",
    "manifest_path": "/opt/airflow/data/raw/writer/2025-11-20/manifest.json",
    "sections": {
      "homepage": "https://writer.com",
      "about": "https://writer.com/company/about",
      "product": "https://writer.com",
      "news": "https://writer.com/newsroom",
      "blog": "https://writer.com/blog",
      "press": null,
      "careers": null,
      "events": "https://writer.com/events",
      "research": "https://writer.com/research",
      "customers": "https://writer.com/customers",
      "resources": "https://writer.com/blog"
    },
    "linkedin_data": {
      "company_profile": "https://www.linkedin.com/company/getwriter",
      "other_social": {
        "twitter": "https://x.com/get_writer"
      },
      "found_on_page": "https://writer.com"
    },
    "status": "success"
  }
}